{"name":"build-javascript","namedChunkGroups":{"polyfill":{"name":"polyfill","assets":[{"name":"webpack-runtime-1bc274b154a87f7b7f13.js","size":4326},{"name":"polyfill-c2926f6e7f51a465593d.js","size":85842}],"filteredAssets":0,"assetsSize":90168,"filteredAuxiliaryAssets":2,"auxiliaryAssetsSize":225481},"app":{"name":"app","assets":[{"name":"webpack-runtime-1bc274b154a87f7b7f13.js","size":4326},{"name":"framework-95260556e650d1674da9.js","size":140546},{"name":"app-d9faf5abddcdcdc7f640.js","size":63237}],"filteredAssets":0,"assetsSize":208109,"filteredAuxiliaryAssets":3,"auxiliaryAssetsSize":624344},"component---src-pages-404-js":{"name":"component---src-pages-404-js","assets":[{"name":"component---src-pages-404-js-679462da56cbcfaf2673.js","size":805}],"filteredAssets":0,"assetsSize":805,"filteredAuxiliaryAssets":1,"auxiliaryAssetsSize":1978},"component---src-pages-index-js":{"name":"component---src-pages-index-js","assets":[{"name":"styles.f7ab3e94bcd07e5817a1.css","size":1263},{"name":"component---src-pages-index-js-a795bbfea9bdd314811e.js","size":106640}],"filteredAssets":0,"assetsSize":107903,"filteredAuxiliaryAssets":13,"auxiliaryAssetsSize":7058055}},"assetsByChunkName":{"polyfill":["webpack-runtime-1bc274b154a87f7b7f13.js","polyfill-c2926f6e7f51a465593d.js"],"app":["webpack-runtime-1bc274b154a87f7b7f13.js","framework-95260556e650d1674da9.js","app-d9faf5abddcdcdc7f640.js"],"component---src-pages-404-js":["component---src-pages-404-js-679462da56cbcfaf2673.js"],"component---src-pages-index-js":["styles.f7ab3e94bcd07e5817a1.css","component---src-pages-index-js-a795bbfea9bdd314811e.js"]},"childAssetsByChunkName":{}}